{
  "by_solver": {
    "jax_fem": {
      "input/rho": {
        "status": "ok",
        "rel_error": 0.0002798410728901936
      },
      "input/hex_mesh": {
        "status": "not_differentiable"
      },
      "input/boundary_conditions": {
        "status": "not_differentiable"
      },
      "output/compliance": {
        "status": "harness_opaque"
      }
    },
    "topopt_jl": {
      "input/rho": {
        "status": "ok",
        "rel_error": 0.0002798410728901936
      },
      "input/hex_mesh": {
        "status": "not_differentiable"
      },
      "input/boundary_conditions": {
        "status": "not_differentiable"
      },
      "input/E": {
        "status": "not_differentiable"
      },
      "input/nu": {
        "status": "not_differentiable"
      },
      "input/xmin": {
        "status": "not_differentiable"
      },
      "output/compliance": {
        "status": "harness_opaque"
      }
    },
    "dealii_structural": {
      "input/rho": {
        "status": "ok",
        "rel_error": 0.0002799174904415016
      },
      "input/hex_mesh": {
        "status": "not_differentiable"
      },
      "input/boundary_conditions": {
        "status": "not_differentiable"
      },
      "input/E_max": {
        "status": "not_differentiable"
      },
      "input/nu": {
        "status": "not_differentiable"
      },
      "input/xmin": {
        "status": "not_differentiable"
      },
      "output/compliance": {
        "status": "harness_opaque"
      }
    },
    "fenics_structural": {
      "input/rho": {
        "status": "ok",
        "rel_error": 0.0002798410728901936
      },
      "input/hex_mesh": {
        "status": "not_differentiable"
      },
      "input/boundary_conditions": {
        "status": "not_differentiable"
      },
      "input/E_max": {
        "status": "not_differentiable"
      },
      "input/nu": {
        "status": "not_differentiable"
      },
      "input/xmin": {
        "status": "not_differentiable"
      },
      "output/compliance": {
        "status": "harness_opaque"
      }
    },
    "firedrake_structural": {
      "input/rho": {
        "status": "ok",
        "rel_error": 0.0002798410728901936
      },
      "input/hex_mesh": {
        "status": "not_differentiable"
      },
      "input/boundary_conditions": {
        "status": "not_differentiable"
      },
      "input/E_max": {
        "status": "not_differentiable"
      },
      "input/nu": {
        "status": "not_differentiable"
      },
      "input/xmin": {
        "status": "not_differentiable"
      },
      "output/compliance": {
        "status": "harness_opaque"
      }
    }
  },
  "params": {
    "ic": {
      "name": "random",
      "seed": 0
    },
    "physics": {
      "nx": 4,
      "ny": 2,
      "nz": 2,
      "Lx": 2.0,
      "Ly": 1.0,
      "Lz": 1.0,
      "F_total": 1.0,
      "corner_load": true
    },
    "fd": {
      "eps": 0.001,
      "n_dirs": 1
    }
  },
  "tesseract_hashes": {
    "dealii_structural": "735398d53b47f392",
    "fenics_structural": "37fb93a57b0aeef5",
    "topopt_jl": "30b2830e1cb90029",
    "firedrake_structural": "f3c927f09cdbd4f8",
    "jax_fem": "c4d160973de083a8"
  },
  "harness_hash": "9810169d944e8e41",
  "harness_fn": "mosaic.benchmarks.suites.gradient.run_differentiability_table",
  "wall_time_s": {
    "jax_fem": 10.569872630992904,
    "topopt_jl": 28.08928392198868,
    "dealii_structural": 9.72672206198331,
    "fenics_structural": 30.046490652952343,
    "firedrake_structural": 37.63253382500261
  }
}